hopsa/__init__.py
hopsa/_modidx.py
hopsa/core.py
hopsa/lgtst.py
hopsa/nbuse.py
hopsa/ossys.py
hopsa-0.3.0.dist-info/METADATA
hopsa-0.3.0.dist-info/WHEEL
hopsa-0.3.0.dist-info/entry_points.txt
hopsa-0.3.0.dist-info/licenses/LICENSE
hopsa-0.3.0.dist-info/RECORD
