Metadata-Version: 2.4
Name: hopsa
Version: 0.3.0
Summary: Utilities that I use regularly
Author-email: Hopsakee <jdejong@posteo.nl>
License-File: LICENSE
Requires-Python: >=3.11
Requires-Dist: ipython>=9.1.0
Requires-Dist: nbformat>=5.10.4
Requires-Dist: pip>=25.0.1
Requires-Dist: pydantic>=2.11.3
Requires-Dist: tomli-w>=1.2.0
